loadingbarcli/__init__.py
loadingbarcli/loadingbarcli.py
loadingbarcli-0.1.2.dist-info/LICENSE
loadingbarcli-0.1.2.dist-info/METADATA
loadingbarcli-0.1.2.dist-info/WHEEL
loadingbarcli-0.1.2.dist-info/top_level.txt
loadingbarcli-0.1.2.dist-info/RECORD
